{
    "imageName": "2025-01-21_09_17_13_716188_check_1_2.png",
    "previous_series": [
        [
            775,
            470
        ],
        [
            785,
            485
        ],
        [
            818,
            483
        ],
        [
            852,
            483
        ],
        [
            887,
            480
        ],
        [
            921,
            478
        ],
        [
            940,
            472
        ],
        [
            935,
            461
        ],
        [
            912,
            457
        ],
        [
            890,
            450
        ],
        [
            873,
            441
        ],
        [
            863,
            429
        ],
        [
            833,
            427
        ],
        [
            802,
            428
        ],
        [
            778,
            437
        ],
        [
            779,
            452
        ],
        [
            781,
            463
        ],
        [
            780,
            471
        ],
        [
            780,
            484
        ],
        [
            774,
            456
        ]
    ],
    "current_series": [
        [
            776,
            484
        ],
        [
            792,
            485
        ],
        [
            827,
            483
        ],
        [
            860,
            482
        ],
        [
            895,
            479
        ],
        [
            928,
            477
        ],
        [
            940,
            468
        ],
        [
            930,
            461
        ],
        [
            908,
            456
        ],
        [
            887,
            448
        ],
        [
            873,
            442
        ],
        [
            858,
            427
        ],
        [
            827,
            428
        ],
        [
            797,
            429
        ],
        [
            779,
            441
        ],
        [
            780,
            455
        ],
        [
            781,
            466
        ],
        [
            782,
            476
        ],
        [
            778,
            484
        ],
        [
            781,
            426
        ]
    ],
    "timestamp": "2025-01-21T09:17:13.716239",
    "similarity_score": 91.21155479080903
}