{
    "imageName": "2025-01-21_14_39_58_938707_check_1_2.png",
    "previous_series": [
        [
            1062,
            595
        ],
        [
            1067,
            592
        ],
        [
            1090,
            584
        ],
        [
            1111,
            570
        ],
        [
            1131,
            562
        ],
        [
            1150,
            552
        ],
        [
            1168,
            540
        ],
        [
            1162,
            538
        ],
        [
            1143,
            538
        ],
        [
            1124,
            541
        ],
        [
            1105,
            548
        ],
        [
            1096,
            553
        ],
        [
            1061,
            573
        ],
        [
            1042,
            585
        ],
        [
            1047,
            593
        ],
        [
            1064,
            593
        ],
        [
            1067,
            596
        ],
        [
            1012,
            545
        ]
    ],
    "current_series": [
        [
            1062,
            596
        ],
        [
            1070,
            592
        ],
        [
            1093,
            582
        ],
        [
            1112,
            569
        ],
        [
            1133,
            560
        ],
        [
            1151,
            551
        ],
        [
            1169,
            541
        ],
        [
            1160,
            537
        ],
        [
            1149,
            538
        ],
        [
            1122,
            541
        ],
        [
            1104,
            549
        ],
        [
            1084,
            561
        ],
        [
            1064,
            572
        ],
        [
            1045,
            584
        ],
        [
            1043,
            592
        ],
        [
            1061,
            593
        ],
        [
            1068,
            598
        ],
        [
            1051,
            572
        ]
    ],
    "timestamp": "2025-01-21T14:39:58.938739",
    "similarity_score": 83.40558437415771
}